toguz.cp312-win_amd64.pyd
toguz-0.5.6.dist-info/METADATA
toguz-0.5.6.dist-info/WHEEL
toguz-0.5.6.dist-info/top_level.txt
toguz-0.5.6.dist-info/RECORD
